README.md
setup.py
yutu/__init__.py
yutu.egg-info/PKG-INFO
yutu.egg-info/SOURCES.txt
yutu.egg-info/dependency_links.txt
yutu.egg-info/not-zip-safe
yutu.egg-info/requires.txt
yutu.egg-info/top_level.txt