Metadata-Version: 1.0
Name: yutu
Version: 2018.9.20.1342
Summary: point cloud representations and movements
Home-page: https://github.com/wdbm/yutu
Author: Will Breaden Madden
Author-email: wbm@protonmail.ch
License: GPLv3
Platform: UNKNOWN
